LICENSE
MANIFEST.in
README.rst
examples.py
requirements.txt
setup.cfg
setup.py
nppr/__init__.py
nppr/settings.py
nppr/tasks.py
nppr/utils.py
nppr.egg-info/PKG-INFO
nppr.egg-info/SOURCES.txt
nppr.egg-info/dependency_links.txt
nppr.egg-info/requires.txt
nppr.egg-info/top_level.txt
nppr/containers/docker-compose.yml
nppr/containers/nginx/Dockerfile
nppr/containers/nginx/mysite.template
nppr/containers/postgres/Dockerfile
nppr/containers/python/Dockerfile